LICENSE
MANIFEST.in
README.md
setup.cfg
setup.py
django_dynamic_breadcrumbs.egg-info/PKG-INFO
django_dynamic_breadcrumbs.egg-info/SOURCES.txt
django_dynamic_breadcrumbs.egg-info/dependency_links.txt
django_dynamic_breadcrumbs.egg-info/requires.txt
django_dynamic_breadcrumbs.egg-info/top_level.txt
docs/Makefile
docs/conf.py
docs/index.rst
docs/dev/tests.rst
docs/guide/install.rst
docs/guide/usage.rst
docs/ref/settings.rst
dynamic_breadcrumbs/__init__.py
dynamic_breadcrumbs/app_settings.py
dynamic_breadcrumbs/apps.py
dynamic_breadcrumbs/context_processors.py
dynamic_breadcrumbs/utils.py
dynamic_breadcrumbs/templates/dynamic_breadcrumbs/breadcrumbs.html
tests/__init__.py
tests/settings.py
tests/tests.py