Metadata-Version: 2.1
Name: django-dynamic-breadcrumbs
Version: 0.4.3
Summary: A Django app to generate HTML breadcrumbs dynamically from URL path
Home-page: https://github.com/marcanuy/django-dynamic-breadcrumbs
Author: Marcelo Canina
Author-email: me@marcanuy.com
License: MIT
Project-URL: Source, https://github.com/marcanuy/django-dynamic-breadcrumbs
Project-URL: Bug Reports, https://github.com/marcanuy/django-dynamic-breadcrumbs/issues
Project-URL: Documentation, https://django-dynamic-breadcrumbs.readthedocs.io/
Keywords: django, breadcrumbs
Classifier: Environment :: Web Environment
Classifier: Framework :: Django
Classifier: Intended Audience :: Developers
Classifier: License :: OSI Approved :: MIT License
Classifier: Operating System :: OS Independent
Classifier: Programming Language :: Python
Classifier: Programming Language :: Python :: 3
Classifier: Programming Language :: Python :: 3 :: Only
Classifier: Programming Language :: Python :: 3.6
Classifier: Programming Language :: Python :: 3.7
Classifier: Programming Language :: Python :: 3.8
Classifier: Topic :: Internet :: WWW/HTTP
Classifier: Topic :: Internet :: WWW/HTTP :: Dynamic Content
Requires-Python: >=3.6
License-File: LICENSE
